memos_mcp_server.py
memos_cmp-0.1.0.dist-info/METADATA
memos_cmp-0.1.0.dist-info/WHEEL
memos_cmp-0.1.0.dist-info/top_level.txt
memos_cmp-0.1.0.dist-info/RECORD
