Metadata-Version: 2.4
Name: memos-cmp
Version: 0.1.0
Summary: Memos MCP服务器
Requires-Python: >=3.13
Requires-Dist: httpx>=0.28.1
Requires-Dist: mcp[cli]>=1.6.0
Requires-Dist: requests>=2.32.3
